reconfigurator/__init__.py
reconfigurator/compiler.py
reconfigurator/reconfigurator.py
reconfigurator/sample.py
reconfigurator/test.py
reconfigurator/config/config.json
reconfigurator/scripts/add_cli.bash
reconfigurator-0.2.7.dist-info/LICENSE
reconfigurator-0.2.7.dist-info/METADATA
reconfigurator-0.2.7.dist-info/WHEEL
reconfigurator-0.2.7.dist-info/top_level.txt
reconfigurator-0.2.7.dist-info/RECORD
