Metadata-Version: 2.1
Name: reconfigurator
Version: 0.2.7
Summary: The purpose of this project is to provide tools for writing experiments. It can be long and slow to come up with all of your parameter files, but reconfigurator makes it a breeze.
Author-email: "Jared J. Beard" <jbeard6@mix.wvu.edu>
Project-URL: Homepage, https://github.com/jaredjbeard/reconfigurator
Project-URL: Documentation, https://reconfigurator.readthedocs.io/en/latest/introduction.html
Classifier: Programming Language :: Python :: 3
Classifier: License :: OSI Approved :: BSD License
Classifier: Operating System :: OS Independent
Requires-Python: >=3.7
License-File: LICENSE
